MANIFEST.in
README.rst
setup.py
src/avifilelib/__about__.py
src/avifilelib/__init__.py
src/avifilelib/avi.py
src/avifilelib/bmp.py
src/avifilelib/data.py
src/avifilelib/decoder.py
src/avifilelib/definition.py
src/avifilelib/enums.py
src/avifilelib/index.py
src/avifilelib/riff.py
src/avifilelib/rle.py
src/avifilelib.egg-info/PKG-INFO
src/avifilelib.egg-info/SOURCES.txt
src/avifilelib.egg-info/dependency_links.txt
src/avifilelib.egg-info/requires.txt
src/avifilelib.egg-info/top_level.txt