Metadata-Version: 1.2
Name: avifilelib
Version: 0.9.1
Summary: A library for reading simple uncompressedor RLE compressed AVI files.
Home-page: https://github.com/michaeluhl/avifilelib
Author: Michael Uhl
License: LGPL
Platform: UNKNOWN
Classifier: Development Status :: 4 - Beta
Classifier: Environment :: Other Environment
Classifier: Intended Audience :: Developers
Classifier: License :: OSI Approved :: GNU Lesser General Public License v3 (LGPLv3)
Classifier: Operating System :: OS Independent
Classifier: Programming Language :: Python :: 3 :: Only
Classifier: Topic :: Software Development :: Libraries :: Application Frameworks
Requires-Python: >=3
